_heapprof.cp37-win_amd64.pyd
heapprof/__init__.py
heapprof/__main__.py
heapprof/_flow_graph.py
heapprof/_si_prefix.py
heapprof/flow_graph.py
heapprof/lowlevel.py
heapprof/reader.py
heapprof/types.py
heapprof/tests/__init__.py
heapprof/tests/end_to_end_test.py
heapprof/tests/si_prefix_test.py
heapprof-1.0.2.dist-info/LICENSE.md
heapprof-1.0.2.dist-info/METADATA
heapprof-1.0.2.dist-info/WHEEL
heapprof-1.0.2.dist-info/top_level.txt
heapprof-1.0.2.dist-info/RECORD
