Metadata-Version: 2.1
Name: heapprof
Version: 1.0.2
Summary: Logging heap profiler
Home-page: UNKNOWN
Author: Yonatan Zunger
Author-email: zunger@humu.com
License: MIT
Project-URL: Documentation, https://humu.github.io/heapprof
Project-URL: Source, https://github.com/humu/heapprof
Project-URL: Tracker, https://github.com/humu/heapprof/issues
Keywords: development profiling memory
Platform: UNKNOWN
Classifier: Development Status :: 5 - Production/Stable
Classifier: License :: OSI Approved :: MIT License
Classifier: Intended Audience :: Developers
Classifier: Programming Language :: Python :: 3.7
Classifier: Programming Language :: Python :: Implementation :: CPython
Requires-Python: >=3.7
